APB/APB_Slave.v
`timescale 1ns/1ns

module slave(
input PCLK, PRESETn,
input PSEL, PENABLE, PWRITE,
input [7:0] PADDR, PWDATA,
output [7:0] PRDATA,
output reg PREADY);
// Declare registers to hold the address and data
reg [7:0] reg_addr;
reg [7:0] mem [0:255];

// Assign the value at the specified address to PRDATA1
assign PRDATA = mem[reg_addr];

always @(*)
begin
    // If PRESETn is low, set PREADY to 0
    if (!PRESETn)
        PREADY = 0;
    else
    begin
        // If PSEL is high and PENABLE and PWRITE are low, set PREADY to 0
        if (PSEL && !PENABLE && !PWRITE)
            PREADY = 0;
        // If PSEL is high and PENABLE is high and PWRITE is low, set PREADY to 1 and set the address to the value on PADDR
        else if (PSEL && PENABLE && !PWRITE)
        begin
            PREADY = 1;
            reg_addr = PADDR;
        end
        // If PSEL is high and PENABLE is low and PWRITE is high, set PREADY to 0
        else if (PSEL && !PENABLE && PWRITE)
            PREADY = 0;
        // If PSEL is high and PENABLE and PWRITE are high, set PREADY to 1 and write the value on PWDATA to the address specified by PADDR
        else if (PSEL && PENABLE && PWRITE)
        begin
            PREADY = 1;
            mem[PADDR] = PWDATA;
        end
        // Otherwise, set PREADY to 0
        else
            PREADY = 0;
    end
 end  
    
endmodule

APB/APB_Master.v
`timescale 1ns/1ns

module apb_bridge(
input [7:0]apb_write_paddr,apb_read_paddr,        // Adresses for read and write operation
input [7:0] apb_write_data,PRDATA,                // Data for write operation, read data from slave
input PRESETn,PCLK,READ_WRITE,transfer,PREADY,    // Reset, clock, read/write, transfer, ready signal
output PSEL,                                      // Select signal for slave
output reg PENABLE,                               // Enable, address, write/read, write data, read data, error signals
output reg [7:0]PADDR,
output reg PWRITE,
output reg [7:0]PWDATA,apb_read_data_out,
output PSLVERR ); 

   

reg [2:0] state, next_state;                     // State and next state variables

reg invalid_setup_error,                        // Error flags
      setup_error,
      invalid_read_paddr,
      invalid_write_paddr,
      invalid_write_data ;
  
localparam IDLE = 3'b001, SETUP = 3'b010, ENABLE = 3'b100 ; // Constant values for state machine



always @(posedge PCLK) // APB Works on rising edge
begin
    if (!PRESETn) // Active Low
        state <= IDLE;
    else
        state <= next_state; 
end



always @(state, transfer, PREADY)
begin
    if (!PRESETn) // Active Low
        next_state = IDLE;
    else
    begin
        PWRITE = ~READ_WRITE;  // Invert read/write signal  , PWRITE=1 indicates APB write access(Master to slave) PWRITE=0 indicates APB read access(Slave to master)
        case (state)
            IDLE:
                begin
                    PENABLE = 0;  // Disable enable signal
                    if (!transfer)
                        next_state = IDLE;  // Stay in IDLE if transfer is not valid
                    else
                        next_state = SETUP;  // Go to SETUP state if transfer is valid
                end
            SETUP:
                begin
                    PENABLE = 0;  // Disable enable signal
                    if (READ_WRITE)
                        PADDR = apb_read_paddr;  // Set adress for read operation
                    else
                    begin
                        PADDR = apb_write_paddr;  // Set adress for write operation
                        PWDATA = apb_write_data;
                    end
                    if (transfer && !PSLVERR)  // Check if transfer is valid and there is no error
                        next_state = ENABLE;    // Go to ENABLE state
                    else
                        next_state = IDLE;
                end
            ENABLE:
                begin
                    if (PSEL)
                        PENABLE = 1;
                    if (transfer & !PSLVERR)
                    begin
                        if (PREADY)
                        begin
                            if (!READ_WRITE)
                                next_state = SETUP;
                            else
                            begin
                                next_state = SETUP;
                                apb_read_data_out = PRDATA;
                            end
                        end
                        else
                            next_state = ENABLE;
                    end
                    else
                        next_state = IDLE;
                end
            default:
                next_state = IDLE;
        endcase
    end
end


 
assign {PSEL} = ((state != IDLE) ? 1'd1 : 1'd0);

  // PSLVERR LOGIC
  
always @(*)
begin
    if (!PRESETn)  // Check if reset is active
    begin        
        setup_error = 0;   // Reset errors
        invalid_read_paddr = 0;
        invalid_write_paddr = 0;
        invalid_write_paddr = 0;
    end
    else
    begin
        if (state == IDLE && next_state == ENABLE) // Check if there is a setup error when moving from IDLE to ENABLE state
            setup_error = 1;
        else
            setup_error = 0;
        if ((apb_write_data === 8'dx) && (!READ_WRITE) && (state == SETUP || state == ENABLE))  // Check if there is an invalid write data when in SETUP or ENABLE state and not in read mode
            invalid_write_data = 1;
        else
            invalid_write_data = 0;
        if ((apb_read_paddr === 8'dx) && READ_WRITE && (state == SETUP || state == ENABLE))     // Check if there is an invalid read address when in SETUP or ENABLE state and in read mode
            invalid_read_paddr = 1;
        else
            invalid_read_paddr = 0;
        if ((apb_write_paddr === 8'dx) && (!READ_WRITE) && (state == SETUP || state == ENABLE)) // Check if there is an invalid write address when in SETUP or ENABLE state and not in read mode
            invalid_write_paddr = 1;
        else
            invalid_write_paddr = 0;
        if (state == SETUP)
        begin
            if (PWRITE)  // Check if there is a setup error when in SETUP state
            begin
                if (PADDR == apb_write_paddr && PWDATA == apb_write_data)  // Check if write address and data match expected values
                    setup_error = 1'b0;
                else
                    setup_error = 1'b1;
            end
            else
            begin
                if (PADDR == apb_read_paddr)   // Check if read address matches expected value
                    setup_error = 1'b0;
                else
                    setup_error = 1'b1;
            end
        end
        else
            setup_error = 1'b0; // Reset setup error when not in SETUP state
    end
    invalid_setup_error = setup_error || invalid_read_paddr || invalid_write_data || invalid_write_paddr;  // Assign invalid setup error to PSLVERR
end
assign PSLVERR = invalid_setup_error;

endmodule

APB/APB_Protcol.v
`include "APB_Master.v"
`include "APB_Slave.v"


`timescale 1ns/1ns

module APB_Protocol(
input PCLK, PRESETn, transfer, READ_WRITE,  // inputs
input [7:0] apb_write_paddr,
input [7:0] apb_write_data,
input [7:0] apb_read_paddr,
output PSLVERR,  // outputs
output [7:0] apb_read_data_out);

// Declare wires for signals used in communication between modules
wire [7:0] PWDATA, PRDATA;
wire [7:0] PADDR;
wire PREADY, PENABLE, PSEL, PWRITE;


// Connect PRDATA to the appropriate value based on READ_WRITE]
// If READ_WRITE is high, PRDATA is passed through
// If READ_WRITE is low, PRDATA is set to 8'dx dont care
assign PRDATA =  PRDATA ;

// Instantiate the masterx,slavex modules
apb_bridge masterx(
    apb_write_paddr,
    apb_read_paddr,
    apb_write_data,
    PRDATA,
    PRESETn,
    PCLK,
    READ_WRITE,
    transfer,
    PREADY,
    PSEL,
    PENABLE,
    PADDR,
    PWRITE,
    PWDATA,
    apb_read_data_out,
    PSLVERR
);

slave slavex(PCLK, PRESETn, PSEL, PENABLE, PWRITE, PADDR[7:0], PWDATA, PRDATA, PREADY);

endmodule

APB/APB_tb.v

`timescale 1ns/1ns

module test;

reg PCLK,PRESETn,transfer,READ_WRITE;
reg [7:0]apb_write_paddr;
reg [7:0]apb_write_data;
reg [7:0]apb_read_paddr;
wire [7:0]apb_read_data_out;
wire PSLVERR;
reg [7:0]data,expected;

reg [7:0]mem[0:255];

APB_Protocol protocolx(  PCLK,
	                       PRESETn,
		                     transfer,
		                     READ_WRITE,
                         apb_write_paddr,
		                     apb_write_data,
		                     apb_read_paddr,
		                     PSLVERR, 
                         apb_read_data_out);
                         
integer i,j;

initial
begin
  PCLK <= 0;
  forever #5 PCLK = ~PCLK;
end


initial $readmemh("check.mem",mem); 
initial
begin
  PRESETn<=0; transfer<=0; READ_WRITE =0;
  @(posedge PCLK)      PRESETn = 1;                                     //no write address available but request for write operation
  @(posedge PCLK)      transfer = 1;
  repeat(2) @(posedge PCLK);
  @(negedge PCLK)      Write_slave;        // write operation
                               
  repeat(2) @(posedge PCLK);    apb_write_paddr = 8'd22; apb_write_data = 8'd35;
  repeat(2) @(posedge PCLK);
  @(posedge PCLK)     READ_WRITE =1; PRESETn<=0; transfer<=0; 
  @(posedge PCLK)     PRESETn = 1;
  repeat(3) @(posedge PCLK)     transfer = 1;                             // no read address available but request for read operation
  repeat(2) @(posedge PCLK)     Read_slave;                             //read operation

  repeat(3) @(posedge PCLK);   apb_read_paddr = 8'd22;                 //data not inserted in write operation but requested for read operation
  repeat(4) @(posedge PCLK);
  $finish;
end


task Write_slave;
begin
  transfer = 1;
  for (i = 0; i < 8; i = i + 1)
  begin
    repeat(2) @(negedge PCLK)
    begin
      data = i;
      apb_write_data = 2*i;
      apb_write_paddr =  data;
    end
  end
 end 
endtask


 
task Read_slave;
begin
  for (j = 0; j < 8; j = j + 1)
  begin
    repeat(2) @(negedge PCLK)
    begin
      data = j;
      apb_read_paddr =  data;
    end
  end
 end 
endtask


 

  initial
   begin
    $dumpfile("apbWaveform.vcd");
    $dumpvars;
   end

 endmodule

APB/apbWaveform.vcd
$date
	Thu Jan 05 13:53:58 2023
$end
$version
	ModelSim Version 10.1d
$end
$timescale
	1ns
$end
$scope module test $end
$var reg 1 ! PCLK $end
$var reg 1 " PRESETn $end
$var reg 1 # transfer $end
$var reg 1 $ READ_WRITE $end
$var reg 8 % apb_write_paddr [7:0] $end
$var reg 8 & apb_write_data [7:0] $end
$var reg 8 ' apb_read_paddr [7:0] $end
$var wire 1 ( apb_read_data_out [7] $end
$var wire 1 ) apb_read_data_out [6] $end
$var wire 1 * apb_read_data_out [5] $end
$var wire 1 + apb_read_data_out [4] $end
$var wire 1 , apb_read_data_out [3] $end
$var wire 1 - apb_read_data_out [2] $end
$var wire 1 . apb_read_data_out [1] $end
$var wire 1 / apb_read_data_out [0] $end
$var wire 1 0 PSLVERR $end
$var reg 8 1 data [7:0] $end
$var reg 8 2 expected [7:0] $end
$var integer 32 3 i $end
$var integer 32 4 j $end
$scope task Write_slave $end
$upscope $end
$scope task Read_slave $end
$upscope $end
$scope module protocolx $end
$var wire 1 5 PCLK $end
$var wire 1 6 PRESETn $end
$var wire 1 7 transfer $end
$var wire 1 8 READ_WRITE $end
$var wire 1 9 apb_write_paddr [7] $end
$var wire 1 : apb_write_paddr [6] $end
$var wire 1 ; apb_write_paddr [5] $end
$var wire 1 < apb_write_paddr [4] $end
$var wire 1 = apb_write_paddr [3] $end
$var wire 1 > apb_write_paddr [2] $end
$var wire 1 ? apb_write_paddr [1] $end
$var wire 1 @ apb_write_paddr [0] $end
$var wire 1 A apb_write_data [7] $end
$var wire 1 B apb_write_data [6] $end
$var wire 1 C apb_write_data [5] $end
$var wire 1 D apb_write_data [4] $end
$var wire 1 E apb_write_data [3] $end
$var wire 1 F apb_write_data [2] $end
$var wire 1 G apb_write_data [1] $end
$var wire 1 H apb_write_data [0] $end
$var wire 1 I apb_read_paddr [7] $end
$var wire 1 J apb_read_paddr [6] $end
$var wire 1 K apb_read_paddr [5] $end
$var wire 1 L apb_read_paddr [4] $end
$var wire 1 M apb_read_paddr [3] $end
$var wire 1 N apb_read_paddr [2] $end
$var wire 1 O apb_read_paddr [1] $end
$var wire 1 P apb_read_paddr [0] $end
$var wire 1 0 PSLVERR $end
$var wire 1 ( apb_read_data_out [7] $end
$var wire 1 ) apb_read_data_out [6] $end
$var wire 1 * apb_read_data_out [5] $end
$var wire 1 + apb_read_data_out [4] $end
$var wire 1 , apb_read_data_out [3] $end
$var wire 1 - apb_read_data_out [2] $end
$var wire 1 . apb_read_data_out [1] $end
$var wire 1 / apb_read_data_out [0] $end
$var wire 1 Q PWDATA [7] $end
$var wire 1 R PWDATA [6] $end
$var wire 1 S PWDATA [5] $end
$var wire 1 T PWDATA [4] $end
$var wire 1 U PWDATA [3] $end
$var wire 1 V PWDATA [2] $end
$var wire 1 W PWDATA [1] $end
$var wire 1 X PWDATA [0] $end
$var wire 1 Y PRDATA [7] $end
$var wire 1 Z PRDATA [6] $end
$var wire 1 [ PRDATA [5] $end
$var wire 1 \ PRDATA [4] $end
$var wire 1 ] PRDATA [3] $end
$var wire 1 ^ PRDATA [2] $end
$var wire 1 _ PRDATA [1] $end
$var wire 1 ` PRDATA [0] $end
$var wire 1 a PADDR [7] $end
$var wire 1 b PADDR [6] $end
$var wire 1 c PADDR [5] $end
$var wire 1 d PADDR [4] $end
$var wire 1 e PADDR [3] $end
$var wire 1 f PADDR [2] $end
$var wire 1 g PADDR [1] $end
$var wire 1 h PADDR [0] $end
$var wire 1 i PREADY $end
$var wire 1 j PENABLE $end
$var wire 1 k PSEL $end
$var wire 1 l PWRITE $end
$scope module masterx $end
$var parameter 3 m IDLE $end
$var parameter 3 n SETUP $end
$var parameter 3 o ENABLE $end
$var wire 1 9 apb_write_paddr [7] $end
$var wire 1 : apb_write_paddr [6] $end
$var wire 1 ; apb_write_paddr [5] $end
$var wire 1 < apb_write_paddr [4] $end
$var wire 1 = apb_write_paddr [3] $end
$var wire 1 > apb_write_paddr [2] $end
$var wire 1 ? apb_write_paddr [1] $end
$var wire 1 @ apb_write_paddr [0] $end
$var wire 1 I apb_read_paddr [7] $end
$var wire 1 J apb_read_paddr [6] $end
$var wire 1 K apb_read_paddr [5] $end
$var wire 1 L apb_read_paddr [4] $end
$var wire 1 M apb_read_paddr [3] $end
$var wire 1 N apb_read_paddr [2] $end
$var wire 1 O apb_read_paddr [1] $end
$var wire 1 P apb_read_paddr [0] $end
$var wire 1 A apb_write_data [7] $end
$var wire 1 B apb_write_data [6] $end
$var wire 1 C apb_write_data [5] $end
$var wire 1 D apb_write_data [4] $end
$var wire 1 E apb_write_data [3] $end
$var wire 1 F apb_write_data [2] $end
$var wire 1 G apb_write_data [1] $end
$var wire 1 H apb_write_data [0] $end
$var wire 1 Y PRDATA [7] $end
$var wire 1 Z PRDATA [6] $end
$var wire 1 [ PRDATA [5] $end
$var wire 1 \ PRDATA [4] $end
$var wire 1 ] PRDATA [3] $end
$var wire 1 ^ PRDATA [2] $end
$var wire 1 _ PRDATA [1] $end
$var wire 1 ` PRDATA [0] $end
$var wire 1 6 PRESETn $end
$var wire 1 5 PCLK $end
$var wire 1 8 READ_WRITE $end
$var wire 1 7 transfer $end
$var wire 1 i PREADY $end
$var wire 1 k PSEL $end
$var reg 1 p PENABLE $end
$var reg 8 q PADDR [7:0] $end
$var reg 1 r PWRITE $end
$var reg 8 s PWDATA [7:0] $end
$var reg 8 t apb_read_data_out [7:0] $end
$var wire 1 0 PSLVERR $end
$var reg 3 u state [2:0] $end
$var reg 3 v next_state [2:0] $end
$var reg 1 w invalid_setup_error $end
$var reg 1 x setup_error $end
$var reg 1 y invalid_read_paddr $end
$var reg 1 z invalid_write_paddr $end
$var reg 1 { invalid_write_data $end
$upscope $end
$scope module slavex $end
$var wire 1 5 PCLK $end
$var wire 1 6 PRESETn $end
$var wire 1 k PSEL $end
$var wire 1 j PENABLE $end
$var wire 1 l PWRITE $end
$var wire 1 a PADDR [7] $end
$var wire 1 b PADDR [6] $end
$var wire 1 c PADDR [5] $end
$var wire 1 d PADDR [4] $end
$var wire 1 e PADDR [3] $end
$var wire 1 f PADDR [2] $end
$var wire 1 g PADDR [1] $end
$var wire 1 h PADDR [0] $end
$var wire 1 Q PWDATA [7] $end
$var wire 1 R PWDATA [6] $end
$var wire 1 S PWDATA [5] $end
$var wire 1 T PWDATA [4] $end
$var wire 1 U PWDATA [3] $end
$var wire 1 V PWDATA [2] $end
$var wire 1 W PWDATA [1] $end
$var wire 1 X PWDATA [0] $end
$var wire 1 Y PRDATA [7] $end
$var wire 1 Z PRDATA [6] $end
$var wire 1 [ PRDATA [5] $end
$var wire 1 \ PRDATA [4] $end
$var wire 1 ] PRDATA [3] $end
$var wire 1 ^ PRDATA [2] $end
$var wire 1 _ PRDATA [1] $end
$var wire 1 ` PRDATA [0] $end
$var reg 1 | PREADY $end
$var reg 8 } reg_addr [7:0] $end
$upscope $end
$upscope $end
$upscope $end
$enddefinitions $end
#0
$dumpvars
0!
0"
0#
0$
bx %
bx &
bx '
bx 1
bx 2
xp
bx q
xr
bx s
bx t
bx u
b1 v
0w
0x
0y
0z
0{
0|
bx }
b1 m
b10 n
b100 o
bx 3
bx 4
x/
x.
x-
x,
x+
x*
x)
x(
00
xX
xW
xV
xU
xT
xS
xR
xQ
x`
x_
x^
x]
x\
x[
xZ
xY
xh
xg
xf
xe
xd
xc
xb
xa
0i
xj
xk
xl
xP
xO
xN
xM
xL
xK
xJ
xI
xH
xG
xF
xE
xD
xC
xB
xA
x@
x?
x>
x=
x<
x;
x:
x9
08
07
06
05
$end
#5
1!
15
1"
16
b1 u
0k
1r
0p
1l
0j
#10
0!
05
#15
1!
15
1#
17
b10 v
#20
0!
05
#25
1!
15
b10 u
1k
1{
1z
1x
1w
b100 v
10
0x
1x
#30
0!
05
#35
1!
15
b100 u
0x
1p
b1 v
1j
1|
1i
#40
0!
05
b0 3
#45
1!
15
b1 u
0k
0|
0{
0z
0w
0p
b10 v
00
0i
0j
#50
0!
05
b0 1
b0 &
b0 %
0@
0?
0>
0=
0<
0;
0:
09
0H
0G
0F
0E
0D
0C
0B
0A
#55
1!
15
b10 u
1k
1x
1w
b0 q
b0 s
b100 v
10
0X
0W
0V
0U
0T
0S
0R
0Q
0h
0g
0f
0e
0d
0c
0b
0a
0x
0w
00
#60
0!
05
b1 3
#65
1!
15
b100 u
1p
1j
1|
1i
b10 v
#70
0!
05
b1 1
b10 &
b1 %
1@
1G
#75
1!
15
b10 u
1x
1w
0p
b1 q
b10 s
b100 v
10
0j
1W
1h
0|
0x
0w
00
0i
#80
0!
05
b10 3
#85
1!
15
b100 u
1p
1j
1|
1i
b10 v
#90
0!
05
b10 1
b100 &
b10 %
0@
1?
0G
1F
#95
1!
15
b10 u
1x
1w
0p
b10 q
b100 s
b100 v
10
0j
0W
1V
0h
1g
0|
0x
0w
00
0i
#100
0!
05
b11 3
#105
1!
15
b100 u
1p
1j
1|
1i
b10 v
#110
0!
05
b11 1
b110 &
b11 %
1@
1G
#115
1!
15
b10 u
1x
1w
0p
b11 q
b110 s
b100 v
10
0j
1W
1h
0|
0x
0w
00
0i
#120
0!
05
b100 3
#125
1!
15
b100 u
1p
1j
1|
1i
b10 v
#130
0!
05
b100 1
b1000 &
b100 %
0@
0?
1>
0G
0F
1E
#135
1!
15
b10 u
1x
1w
0p
b100 q
b1000 s
b100 v
10
0j
0W
0V
1U
0h
0g
1f
0|
0x
0w
00
0i
#140
0!
05
b101 3
#145
1!
15
b100 u
1p
1j
1|
1i
b10 v
#150
0!
05
b101 1
b1010 &
b101 %
1@
1G
#155
1!
15
b10 u
1x
1w
0p
b101 q
b1010 s
b100 v
10
0j
1W
1h
0|
0x
0w
00
0i
#160
0!
05
b110 3
#165
1!
15
b100 u
1p
1j
1|
1i
b10 v
#170
0!
05
b110 1
b1100 &
b110 %
0@
1?
0G
1F
#175
1!
15
b10 u
1x
1w
0p
b110 q
b1100 s
b100 v
10
0j
0W
1V
0h
1g
0|
0x
0w
00
0i
#180
0!
05
b111 3
#185
1!
15
b100 u
1p
1j
1|
1i
b10 v
#190
0!
05
b111 1
b1110 &
b111 %
1@
1G
#195
1!
15
b10 u
1x
1w
0p
b111 q
b1110 s
b100 v
10
0j
1W
1h
0|
0x
0w
00
0i
#200
0!
05
b1000 3
#205
1!
15
b100 u
1p
1j
1|
1i
b10 v
#210
0!
05
#215
1!
15
b10110 %
b100011 &
1H
0F
0E
1C
0@
1<
b10 u
1x
1w
0p
b10110 q
b100011 s
b100 v
10
0j
1X
0V
0U
1S
0h
1d
0|
0x
0w
00
0i
#220
0!
05
#225
1!
15
b100 u
1p
1j
1|
1i
b10 v
#230
0!
05
#235
1!
15
b10 u
0p
b100 v
0j
0|
0i
#240
0!
05
#245
1!
15
1$
18
1y
1w
10
b100 u
0"
0#
06
07
0y
0w
b1 v
00
#250
0!
05
#255
1!
15
1"
16
1y
1w
10
b1 u
0k
0y
0w
0r
00
0l
#260
0!
05
#265
1!
15
1#
17
b10 v
#270
0!
05
#275
1!
15
b10 u
1k
1y
1x
1w
bx q
b100 v
10
xh
xg
xf
xe
xd
xc
xb
xa
0x
1x
#280
0!
05
#285
1!
15
b100 u
0x
1p
b1 v
1j
1|
1i
#290
0!
05
#295
1!
15
b0 4
b1 u
0k
0|
0y
0w
0p
b10 v
00
0i
0j
#300
0!
05
b0 1
b0 '
0P
0O
0N
0M
0L
0K
0J
0I
#305
1!
15
b10 u
1k
1x
1w
b0 q
b100 v
10
0h
0g
0f
0e
0d
0c
0b
0a
0x
0w
00
#310
0!
05
b1 4
#315
1!
15
b100 u
1p
1j
1|
b0 }
1i
b10 v
#320
0!
05
b1 1
b1 '
1P
#325
1!
15
b10 u
1x
1w
0p
b1 q
b100 v
10
0j
1h
0|
0x
0w
00
0i
#330
0!
05
b10 4
#335
1!
15
b100 u
1p
1j
1|
b1 }
1i
b10 v
#340
0!
05
b10 1
b10 '
0P
1O
#345
1!
15
b10 u
1x
1w
0p
b10 q
b100 v
10
0j
0h
1g
0|
0x
0w
00
0i
#350
0!
05
b11 4
#355
1!
15
b100 u
1p
1j
1|
b10 }
1i
b10 v
#360
0!
05
b11 1
b11 '
1P
#365
1!
15
b10 u
1x
1w
0p
b11 q
b100 v
10
0j
1h
0|
0x
0w
00
0i
#370
0!
05
b100 4
#375
1!
15
b100 u
1p
1j
1|
b11 }
1i
b10 v
#380
0!
05
b100 1
b100 '
0P
0O
1N
#385
1!
15
b10 u
1x
1w
0p
b100 q
b100 v
10
0j
0h
0g
1f
0|
0x
0w
00
0i
#390
0!
05
b101 4
#395
1!
15
b100 u
1p
1j
1|
b100 }
1i
b10 v
#400
0!
05
b101 1
b101 '
1P
#405
1!
15
b10 u
1x
1w
0p
b101 q
b100 v
10
0j
1h
0|
0x
0w
00
0i
#410
0!
05
b110 4
#415
1!
15
b100 u
1p
1j
1|
b101 }
1i
b10 v
#420
0!
05
b110 1
b110 '
0P
1O
#425
1!
15
b10 u
1x
1w
0p
b110 q
b100 v
10
0j
0h
1g
0|
0x
0w
00
0i
#430
0!
05
b111 4
#435
1!
15
b100 u
1p
1j
1|
b110 }
1i
b10 v
#440
0!
05
b111 1
b111 '
1P
#445
1!
15
b10 u
1x
1w
0p
b111 q
b100 v
10
0j
1h
0|
0x
0w
00
0i
#450
0!
05
b1000 4
#455
1!
15
b0 4
b100 u
1p
1j
1|
b111 }
1i
b10 v
#460
0!
05
b0 1
b0 '
0P
0O
0N
#465
1!
15
b10 u
1x
1w
0p
b0 q
b100 v
10
0j
0h
0g
0f
0|
0x
0w
00
0i
#470
0!
05
b1 4
#475
1!
15
b100 u
1p
1j
1|
b0 }
1i
b10 v
#480
0!
05
b1 1
b1 '
1P
#485
1!
15
b10 u
1x
1w
0p
b1 q
b100 v
10
0j
1h
0|
0x
0w
00
0i
#490
0!
05
b10 4
#495
1!
15
b100 u
1p
1j
1|
b1 }
1i
b10 v
#500
0!
05
b10 1
b10 '
0P
1O
#505
1!
15
b10 u
1x
1w
0p
b10 q
b100 v
10
0j
0h
1g
0|
0x
0w
00
0i
#510
0!
05
b11 4
#515
1!
15
b100 u
1p
1j
1|
b10 }
1i
b10 v
#520
0!
05
b11 1
b11 '
1P
#525
1!
15
b10 u
1x
1w
0p
b11 q
b100 v
10
0j
1h
0|
0x
0w
00
0i
#530
0!
05
b100 4
#535
1!
15
b100 u
1p
1j
1|
b11 }
1i
b10 v
#540
0!
05
b100 1
b100 '
0P
0O
1N
#545
1!
15
b10 u
1x
1w
0p
b100 q
b100 v
10
0j
0h
0g
1f
0|
0x
0w
00
0i
#550
0!
05
b101 4
#555
1!
15
b100 u
1p
1j
1|
b100 }
1i
b10 v
#560
0!
05
b101 1
b101 '
1P
#565
1!
15
b10 u
1x
1w
0p
b101 q
b100 v
10
0j
1h
0|
0x
0w
00
0i
#570
0!
05
b110 4
#575
1!
15
b100 u
1p
1j
1|
b101 }
1i
b10 v
#580
0!
05
b110 1
b110 '
0P
1O
#585
1!
15
b10 u
1x
1w
0p
b110 q
b100 v
10
0j
0h
1g
0|
0x
0w
00
0i
#590
0!
05
b111 4
#595
1!
15
b100 u
1p
1j
1|
b110 }
1i
b10 v
#600
0!
05
b111 1
b111 '
1P
